newsFeedClassifier-CS331/ExceptionNotSeen.py
newsFeedClassifier-CS331/__init__.py
newsFeedClassifier-CS331/classifier.py
newsFeedClassifier-CS331/tokenizer.py
newsFeedClassifier-CS331/trainedData.py
newsFeedClassifier-CS331/trainer.py
newsFeedClassifierCS331/ExceptionNotSeen.py
newsFeedClassifierCS331/__init__.py
newsFeedClassifierCS331/classifier.py
newsFeedClassifierCS331/tokenizer.py
newsFeedClassifierCS331/trainedData.py
newsFeedClassifierCS331/trainer.py
newsFeedClassifierCS331-2.0.1.dist-info/DESCRIPTION.rst
newsFeedClassifierCS331-2.0.1.dist-info/METADATA
newsFeedClassifierCS331-2.0.1.dist-info/RECORD
newsFeedClassifierCS331-2.0.1.dist-info/WHEEL
newsFeedClassifierCS331-2.0.1.dist-info/metadata.json
newsFeedClassifierCS331-2.0.1.dist-info/top_level.txt
