Metadata-Version: 2.0
Name: newsFeedClassifierCS331
Version: 2.0.1
Summary: news feed classifier using naive bayes algorithm
Home-page: UNKNOWN
Author: CS331 Group: Dot Slash
Author-email: artificialintelligence@pern.edu.pk
License: LUMS
Platform: any
